ethical_gen/__init__.py
ethical_gen/config.py
ethical_gen/formats/__init__.py
ethical_gen/formats/alpaca.py
ethical_gen/formats/base.py
ethical_gen/formats/chatml.py
ethical_gen/formats/sharegpt.py
ethical_gen/generator.py
ethical_gen/main.py
ethical_gen/prompts/__init__.py
ethical_gen/prompts/loader.py
ethical_gen/validator.py
ethical_response_generator-0.1.0.dist-info/METADATA
ethical_response_generator-0.1.0.dist-info/WHEEL
ethical_response_generator-0.1.0.dist-info/entry_points.txt
ethical_response_generator-0.1.0.dist-info/licenses/LICENSE
ethical_response_generator-0.1.0.dist-info/RECORD
