Metadata-Version: 2.4
Name: ethical-response-generator
Version: 0.1.0
Summary: Generate validated ethical responses to challenging prompts using Constitutional AI (CAI) models
License: MIT
License-File: LICENSE
Author: dlattka
Author-email: dennislattka@gmail.com
Requires-Python: >=3.10
Classifier: License :: OSI Approved :: MIT License
Classifier: Programming Language :: Python :: 3
Classifier: Programming Language :: Python :: 3.10
Classifier: Programming Language :: Python :: 3.11
Classifier: Programming Language :: Python :: 3.12
Classifier: Programming Language :: Python :: 3.13
Classifier: Programming Language :: Python :: 3.14
Requires-Dist: aiohttp (>=3.9.0)
Requires-Dist: anthropic (>=0.40.0)
Requires-Dist: datasets (>=2.14.0)
Requires-Dist: openai (>=1.0.0)
Requires-Dist: pydantic (>=2.0.0)
Requires-Dist: rich (>=13.0.0)
Requires-Dist: tomli (>=2.0.0)
Requires-Dist: tqdm (>=4.65.0)
Requires-Dist: typer (>=0.9.0)
